huaweicloudsdkdcos/__init__.py
huaweicloudsdkdcos/v1/__init__.py
huaweicloudsdkdcos/v1/dcos_async_client.py
huaweicloudsdkdcos/v1/dcos_client.py
huaweicloudsdkdcos/v1/model/__init__.py
huaweicloudsdkdcos/v1/model/access_white_list.py
huaweicloudsdkdcos/v1/model/asset.py
huaweicloudsdkdcos/v1/model/asset_info.py
huaweicloudsdkdcos/v1/model/asset_list_request_body.py
huaweicloudsdkdcos/v1/model/asset_service_details.py
huaweicloudsdkdcos/v1/model/contact_information.py
huaweicloudsdkdcos/v1/model/contact_service_details.py
huaweicloudsdkdcos/v1/model/default_sop.py
huaweicloudsdkdcos/v1/model/delivery_info.py
huaweicloudsdkdcos/v1/model/device_service_details.py
huaweicloudsdkdcos/v1/model/field_entity.py
huaweicloudsdkdcos/v1/model/list_order_request.py
huaweicloudsdkdcos/v1/model/list_order_response.py
huaweicloudsdkdcos/v1/model/operation_object.py
huaweicloudsdkdcos/v1/model/order_catalogue.py
huaweicloudsdkdcos/v1/model/order_item.py
huaweicloudsdkdcos/v1/model/order_log.py
huaweicloudsdkdcos/v1/model/order_service_details.py
huaweicloudsdkdcos/v1/model/order_verification.py
huaweicloudsdkdcos/v1/model/pagination.py
huaweicloudsdkdcos/v1/model/save_order_body.py
huaweicloudsdkdcos/v1/model/save_order_request.py
huaweicloudsdkdcos/v1/model/save_order_response.py
huaweicloudsdkdcos/v1/model/show_order_catalogue_request.py
huaweicloudsdkdcos/v1/model/show_order_catalogue_response.py
huaweicloudsdkdcos/v1/model/show_order_information_request.py
huaweicloudsdkdcos/v1/model/show_order_information_response.py
huaweicloudsdkdcos/v1/model/show_order_request.py
huaweicloudsdkdcos/v1/model/show_order_response.py
huaweicloudsdkdcos/v1/model/show_page_asset_list_result_request.py
huaweicloudsdkdcos/v1/model/show_page_asset_list_result_response.py
huaweicloudsdkdcos/v1/model/upload_file_info.py
huaweicloudsdkdcos/v1/model/upload_file_request.py
huaweicloudsdkdcos/v1/model/upload_file_request_body.py
huaweicloudsdkdcos/v1/model/upload_file_response.py
huaweicloudsdkdcos-3.1.184.dist-info/METADATA
huaweicloudsdkdcos-3.1.184.dist-info/WHEEL
huaweicloudsdkdcos-3.1.184.dist-info/licenses/LICENSE
huaweicloudsdkdcos-3.1.184.dist-info/RECORD
